mypkg/__init__.py
mypkg/curvefit.py
mypkg/stattest.py
mypkg_marchfra-0.0.4.dist-info/LICENSE
mypkg_marchfra-0.0.4.dist-info/METADATA
mypkg_marchfra-0.0.4.dist-info/WHEEL
mypkg_marchfra-0.0.4.dist-info/top_level.txt
mypkg_marchfra-0.0.4.dist-info/RECORD
