Metadata-Version: 2.1
Name: mypkg-marchfra
Version: 0.0.4
Summary: A package with all the functions I use
Home-page: https://github.com/marchfra/sampleproject
Author: marchfra
Author-email: marchfra@gmail.com
License: UNKNOWN
Platform: UNKNOWN
Classifier: Programming Language :: Python :: 3
Classifier: License :: OSI Approved :: MIT License
Classifier: Operating System :: MacOS
Requires-Python: >=3.6
License-File: LICENSE
